LICENSE
MANIFEST.in
README.md
setup.py
altair_widgets/__init__.py
altair_widgets/widget.py
altair_widgets.egg-info/PKG-INFO
altair_widgets.egg-info/SOURCES.txt
altair_widgets.egg-info/dependency_links.txt
altair_widgets.egg-info/requires.txt
altair_widgets.egg-info/top_level.txt