Metadata-Version: 1.1
Name: altair-widgets
Version: 0.1.0
Summary: Altair Widgets: An interactive visualization for statistical data for Python.
Home-page: http://altair-viz.github.io
Author: Scott Sievert
Author-email: me@scottsievert.com
License: BSD 3-clause
Download-URL: http://github.com/altair-viz/altair_widgets/
Platform: UNKNOWN
Classifier: Development Status :: 4 - Beta
Classifier: Environment :: Console
Classifier: Intended Audience :: Science/Research
Classifier: License :: OSI Approved :: BSD License
Classifier: Natural Language :: English
Classifier: Programming Language :: Python :: 2.7
Classifier: Programming Language :: Python :: 3.4
Classifier: Programming Language :: Python :: 3.5
